flake8_aggressive/__init__.py
flake8_aggressive-1.1.10.dist-info/LICENSE
flake8_aggressive-1.1.10.dist-info/WHEEL
flake8_aggressive-1.1.10.dist-info/METADATA
flake8_aggressive-1.1.10.dist-info/RECORD
