Metadata-Version: 2.1
Name: flake8-aggressive
Version: 1.1.10
Summary: Flake8 aggressive plugins pack
Home-page: https://pypi.org/project/flake8-aggreessive
License: MIT
Keywords: flake8,plugin
Author: Austin Page
Author-email: jaustinpage@gmail.com
Requires-Python: >=3.7.2,<4.0.0
Classifier: License :: OSI Approved :: MIT License
Classifier: Programming Language :: Python :: 3
Classifier: Programming Language :: Python :: 3.10
Classifier: Programming Language :: Python :: 3.8
Classifier: Programming Language :: Python :: 3.9
Requires-Dist: darglint (>=1.8.1)
Requires-Dist: flake8 (==4.0.1)
Requires-Dist: flake8-2020 (>=1.6.1)
Requires-Dist: flake8-absolute-import (>=1.0.0.1)
Requires-Dist: flake8-annotations (>=2.9.1)
Requires-Dist: flake8-annotations-complexity (>=0.0.7)
Requires-Dist: flake8-bandit (>=3.0.0)
Requires-Dist: flake8-blind-except (>=0.2.1)
Requires-Dist: flake8-broken-line (>=0.5.0)
Requires-Dist: flake8-bugbear (>=22.8.23)
Requires-Dist: flake8-builtins (>=1.5.3)
Requires-Dist: flake8-class-attributes-order (>=0.1.3)
Requires-Dist: flake8-comprehensions (>=3.10.0)
Requires-Dist: flake8-datetimez (>=20.10.0)
Requires-Dist: flake8-debugger (>=4.1.2)
Requires-Dist: flake8-eradicate (>=1.3.0)
Requires-Dist: flake8-executable (>=2.1.1)
Requires-Dist: flake8-expression-complexity (>=0.0.11)
Requires-Dist: flake8-fixme (>=1.1.1)
Requires-Dist: flake8-isort (>=4.2.0)
Requires-Dist: flake8-logging-format (>=0.7.5)
Requires-Dist: flake8-no-implicit-concat (>=0.3.3)
Requires-Dist: flake8-pep3101 (>=1.3.0)
Requires-Dist: flake8-print (>=5.0.0)
Requires-Dist: flake8-pytest (>=1.4)
Requires-Dist: flake8-pytest-style (>=1.6.0)
Requires-Dist: flake8-raise (>=0.0.5)
Requires-Dist: flake8-requirements (>=1.6.0)
Requires-Dist: flake8-return (>=1.1.3)
Requires-Dist: flake8-simplify (>=0.19.3)
Requires-Dist: flake8-strftime (>=0.3.2)
Requires-Dist: flake8-string-format (>=0.3.0)
Requires-Dist: flake8-super (>=0.1.3)
Requires-Dist: flake8-use-pathlib (>=0.3.0)
Requires-Dist: flakeheaven (>=3.0.0)
Requires-Dist: pep8-naming (>=0.13.1)
Requires-Dist: pylint (>=2.14.5)
Project-URL: Repository, https://github.com/jaustinpage/flake8-aggressive
